abconfig/__init__.py
abconfig/common.py
abconfig/env.py
abconfig/file.py
abconfig/settings.py
abconfig/utils.py
abconfig/vault.py
abconfig-1.0.12.dist-info/LICENSE
abconfig-1.0.12.dist-info/METADATA
abconfig-1.0.12.dist-info/WHEEL
abconfig-1.0.12.dist-info/top_level.txt
abconfig-1.0.12.dist-info/RECORD
