Metadata-Version: 2.1
Name: abconfig
Version: 1.0.12
Summary: Simple and powerful configuration manager for Python projects
Home-page: https://github.com/kudato/abconfig.git
Author: Alexander Shevchenko
Author-email: kudato@me.com
License: MIT
Platform: UNKNOWN
Classifier: Intended Audience :: Developers
Classifier: License :: OSI Approved :: MIT License
Classifier: Programming Language :: Python
Classifier: Programming Language :: Python :: 3.6
Classifier: Programming Language :: Python :: 3.7
Classifier: Operating System :: POSIX
Classifier: Operating System :: MacOS :: MacOS X
Classifier: Development Status :: 5 - Production/Stable
Classifier: Topic :: Software Development :: Libraries :: Python Modules
Classifier: Topic :: Utilities
Requires-Python: >=3.6.0
Provides-Extra: aws
Requires-Dist: boto3 (>=1.10.45) ; extra == 'aws'
Provides-Extra: toml
Requires-Dist: toml (>=0.10.0) ; extra == 'toml'
Provides-Extra: vault
Requires-Dist: hvac (<0.11.2,>=0.9.6) ; extra == 'vault'
Provides-Extra: yaml
Requires-Dist: pyyaml (>=5.1) ; extra == 'yaml'
